ccacb/__init__.py
ccacb/watchclipboard.py
ccacb-0.6.10.dist-info/entry_points.txt
ccacb-0.6.10.dist-info/WHEEL
ccacb-0.6.10.dist-info/METADATA
ccacb-0.6.10.dist-info/RECORD
