Metadata-Version: 2.1
Name: ccacb
Version: 0.6.10
Summary: Watches the clipboard for youtube urls and downloads them
Home-page: https://github.com/ccdale/ccacb
License: GPL-3.0-or-later
Author: Chris Allison
Author-email: chris.charles.allison+ccacb@gmail.com
Requires-Python: >=3.7,<4.0
Classifier: License :: OSI Approved :: GNU General Public License v3 or later (GPLv3+)
Classifier: Programming Language :: Python :: 3
Classifier: Programming Language :: Python :: 3.7
Classifier: Programming Language :: Python :: 3.8
Requires-Dist: ccaconfig (>=0.3.3,<0.4.0)
Requires-Dist: ccalogging (>=0.3.3,<0.4.0)
Requires-Dist: pyperclip (>=1.8.0,<2.0.0)
Project-URL: Repository, https://github.com/ccdale/ccacb
